<annotation>
	<folder>new_hippo_dataset</folder>
	<filename>hippo_00000450.jpg</filename>
	<path>hippo_00000450.jpg</path>
	<source>
		<database>Unknown</database>
	</source>
	<size>
		<width>800</width>
		<height>450</height>
		<depth>3</depth>
	</size>
	<segmented>0</segmented>
	<object>
		<name>hipopotamo</name>
		<pose>Unspecified</pose>
		<truncated>0</truncated>
		<difficult>0</difficult>
		<bndbox>
			<xmin>265</xmin>
			<ymin>103</ymin>
			<xmax>434</xmax>
			<ymax>300</ymax>
		</bndbox>
	</object>
	<object>
		<name>hipopotamo</name>
		<pose>Unspecified</pose>
		<truncated>0</truncated>
		<difficult>0</difficult>
		<bndbox>
			<xmin>373</xmin>
			<ymin>94</ymin>
			<xmax>500</xmax>
			<ymax>202</ymax>
		</bndbox>
	</object>
</annotation>
