<annotation>
	<folder>new_hippo_dataset</folder>
	<filename>hippo_00000036.jpg</filename>
	<path>hippo_00000036.jpg</path>
	<source>
		<database>Unknown</database>
	</source>
	<size>
		<width>800</width>
		<height>450</height>
		<depth>3</depth>
	</size>
	<segmented>0</segmented>
	<object>
		<name>hipopotamo</name>
		<pose>Unspecified</pose>
		<truncated>0</truncated>
		<difficult>0</difficult>
		<bndbox>
			<xmin>427</xmin>
			<ymin>136</ymin>
			<xmax>693</xmax>
			<ymax>282</ymax>
		</bndbox>
	</object>
	<object>
		<name>hipopotamo</name>
		<pose>Unspecified</pose>
		<truncated>0</truncated>
		<difficult>0</difficult>
		<bndbox>
			<xmin>438</xmin>
			<ymin>238</ymin>
			<xmax>559</xmax>
			<ymax>307</ymax>
		</bndbox>
	</object>
</annotation>
